pydap/__init__.py
pydap/_version.py
pydap/client.py
pydap/exceptions.py
pydap/lib.py
pydap/model.py
pydap/net.py
pydap/pycompat.py
pydap/apis/__init__.py
pydap/apis/netcdf4.py
pydap/cas/__init__.py
pydap/cas/esgf.py
pydap/cas/get_cookies.py
pydap/cas/urs.py
pydap/handlers/dap.py
pydap/handlers/lib.py
pydap/handlers/csv/__init__.py
pydap/handlers/netcdf/__init__.py
pydap/logo/pydap-ico.png
pydap/logo/pydap-ico.svg
pydap/logo/pydap.png
pydap/logo/pydap.svg
pydap/parsers/__init__.py
pydap/parsers/das.py
pydap/parsers/dds.py
pydap/parsers/dmr.py
pydap/responses/__init__.py
pydap/responses/ascii.py
pydap/responses/das.py
pydap/responses/dds.py
pydap/responses/dmr.py
pydap/responses/dods.py
pydap/responses/error.py
pydap/responses/lib.py
pydap/responses/version.py
pydap/responses/html/__init__.py
pydap/responses/html/templates/html.html
pydap/responses/html/templates/macros.html
pydap/server/__init__.py
pydap/server/devel.py
pydap/server/devel_ssl.py
pydap/tests/__init__.py
pydap/tests/datasets.py
pydap/tests/test_D1.py
pydap/tests/test_cas_esgf.py
pydap/tests/test_client.py
pydap/tests/test_constrain.py
pydap/tests/test_dapper.py
pydap/tests/test_exceptions.py
pydap/tests/test_handlers_csv.py
pydap/tests/test_handlers_dap.py
pydap/tests/test_handlers_lib.py
pydap/tests/test_handlers_netcdf.py
pydap/tests/test_iter_data.py
pydap/tests/test_lib.py
pydap/tests/test_model.py
pydap/tests/test_net.py
pydap/tests/test_open_dap4_url.py
pydap/tests/test_parsers.py
pydap/tests/test_parsers_dap.py
pydap/tests/test_parsers_das.py
pydap/tests/test_parsers_dds.py
pydap/tests/test_parsers_dmr.py
pydap/tests/test_pydap.py
pydap/tests/test_responses_ascii.py
pydap/tests/test_responses_das.py
pydap/tests/test_responses_dds.py
pydap/tests/test_responses_dmr.py
pydap/tests/test_responses_dods.py
pydap/tests/test_responses_error.py
pydap/tests/test_responses_html.py
pydap/tests/test_responses_lib.py
pydap/tests/test_responses_version.py
pydap/tests/test_server_devel.py
pydap-3.5.7.dist-info/licenses/LICENSE
pydap-3.5.7.dist-info/METADATA
pydap-3.5.7.dist-info/WHEEL
pydap-3.5.7.dist-info/entry_points.txt
pydap-3.5.7.dist-info/top_level.txt
pydap-3.5.7.dist-info/RECORD
