Metadata-Version: 2.4
Name: pydap
Version: 3.5.7
Summary: A pure python implementation of the Data Access Protocol.
Author-email: Roberto De Almeida <roberto@dealmeida.net>
Maintainer-email: Miguel Jimenez-Urias <mjimenez@opendap.org>
License: The MIT License
Classifier: Development Status :: 5 - Production/Stable
Classifier: Intended Audience :: Science/Research
Classifier: Programming Language :: Python
Classifier: Programming Language :: Python :: 3
Classifier: Programming Language :: Python :: 3.10
Classifier: Programming Language :: Python :: 3.11
Classifier: Programming Language :: Python :: 3.12
Classifier: Programming Language :: Python :: 3.13
Classifier: Operating System :: MacOS
Classifier: Operating System :: Microsoft :: Windows
Classifier: Operating System :: POSIX
Classifier: Topic :: Internet :: WWW/HTTP :: WSGI
Classifier: Topic :: Scientific/Engineering
Classifier: License :: OSI Approved :: MIT License
Requires-Python: >=3.10
License-File: LICENSE
Requires-Dist: numpy
Requires-Dist: requests
Requires-Dist: requests-cache
Requires-Dist: scipy
Requires-Dist: Webob
Requires-Dist: beautifulsoup4
Requires-Dist: lxml
Provides-Extra: docs
Requires-Dist: Sphinx; extra == "docs"
Requires-Dist: Pygments; extra == "docs"
Requires-Dist: pandoc; extra == "docs"
Requires-Dist: sphinx_rtd_theme; extra == "docs"
Requires-Dist: nbsphinx; extra == "docs"
Requires-Dist: numpydoc; extra == "docs"
Provides-Extra: netcdf
Requires-Dist: netCDF4; extra == "netcdf"
Provides-Extra: server
Requires-Dist: werkzeug>=2.2.2; extra == "server"
Requires-Dist: gunicorn; extra == "server"
Requires-Dist: PasteDeploy; extra == "server"
Requires-Dist: docopt-ng; extra == "server"
Requires-Dist: cryptography; extra == "server"
Requires-Dist: gsw; extra == "server"
Requires-Dist: coards; extra == "server"
Requires-Dist: Jinja2; extra == "server"
Dynamic: license-file
